{
  "name": "Avatar",
  "slug": "avatar",
  "isIcon": false,
  "figmaNodeIds": [
    "1685:347",
    "1685:346",
    "1686:38",
    "1686:124",
    "1685:345",
    "1686:41",
    "1686:127",
    "1685:343",
    "1686:44",
    "1880:2546",
    "1686:130",
    "1880:2560",
    "1685:342",
    "1880:2283",
    "1686:47",
    "1880:2552",
    "1686:133",
    "1880:2570",
    "1685:344",
    "1880:2290",
    "1686:50",
    "1686:136",
    "1685:341",
    "1686:53",
    "1686:139",
    "1685:340",
    "1686:56",
    "1686:142",
    "1685:339",
    "1686:59",
    "1686:145",
    "1685:338",
    "1686:62",
    "1686:148",
    "1685:337",
    "1686:65",
    "1686:151"
  ],
  "variants": [
    {
      "name": "Theme: Light"
    },
    {
      "name": "Size: 24 px"
    },
    {
      "name": "Type: Img"
    },
    {
      "name": "Square: On"
    },
    {
      "name": "Type: Text"
    },
    {
      "name": "Type: Icon"
    },
    {
      "name": "Square: Off"
    },
    {
      "name": "Size: 32 px"
    },
    {
      "name": "Size: 40 px"
    },
    {
      "name": "Size: 48 px"
    },
    {
      "name": "Size: 64 px"
    },
    {
      "name": "Size: 96 px"
    }
  ],
  "states": [],
  "contract": {
    "props": [],
    "cssVariables": [],
    "classNames": []
  }
}
